{
  "dependencies": {
    "mssql1": {
      "type": "mssql.local",
      "connectionId": "ConnectionStrings:MercuryHealthWebContext"
    },
    "secrets1": {
      "type": "secrets.user"
    },
    "appInsights1": {
      "secretStore": "LocalSecretsFile",
      "resourceId": "/subscriptions/[parameters('subscriptionId')]/resourceGroups/[parameters('resourceGroupName')]/providers/microsoft.insights/components/appi-fq3ruuhxgjony",
      "type": "appInsights.azure",
      "connectionId": "APPLICATIONINSIGHTS_CONNECTION_STRING"
    },
    "appConfig1": {
      "secretStore": "LocalSecretsFile",
      "resourceId": "/subscriptions/[parameters('subscriptionId')]/resourceGroups/[parameters('resourceGroupName')]/providers/Microsoft.AppConfiguration/configurationStores/appcs-fq3ruuhxgjony",
      "type": "appConfig.azure",
      "connectionId": "AppConfig"
    }
  }
}